wavelength/__init__.py
wavelength/aws/__init__.py
wavelength/aws/aws_args.py
wavelength/aws/boto_helper.py
wavelength/config/__init__.py
wavelength/dal/__init__.py
wavelength/dal/dal_config.py
wavelength/dal/dao/__init__.py
wavelength/dal/dao/commands/__init__.py
wavelength/dal/dao/commands/aquire_lock_pynamo_command.py
wavelength/dal/dao/commands/base_update_pynamo_command.py
wavelength/dal/dao/commands/create_pynamo_command.py
wavelength/dal/dao/commands/delete_pynamo_command.py
wavelength/dal/dao/commands/get_by_key_pynamo_command.py
wavelength/dal/dao/commands/post_filter_pynamo_command.py
wavelength/dal/dao/commands/pynamo_command.py
wavelength/dal/dao/commands/pynamo_query_args.py
wavelength/dal/dao/commands/query_pynamo_command.py
wavelength/dal/dao/commands/soft_delete_pynamo_command.py
wavelength/dal/dao/commands/update_pynamo_command.py
wavelength/dal/dao/models/__init__.py
wavelength/dal/dao/models/observable_persistence_model.py
wavelength/dal/dao/models/platform_persistence_model.py
wavelength/dal/dao/models/pynamo_crud_model.py
wavelength/dal/dynamodb/__init__.py
wavelength/dal/dynamodb/util.py
wavelength/dal/pynamo_models/__init__.py
wavelength/dal/pynamo_models/cachable_pynamo_model.py
wavelength/dal/pynamo_models/util.py
wavelength/dal/pynamo_models/attributes/__init__.py
wavelength/dal/pynamo_models/attributes/compressed_json_attribute.py
wavelength/dal/pynamo_models/attributes/epoch_attribute.py
wavelength/dal/pynamo_models/attributes/tag_attribute.py
wavelength/errors/__init__.py
wavelength/errors/exceptions.py
wavelength/logging/__init__.py
wavelength/logging/filter.py
wavelength/logging/log_lambda_base.py
wavelength/logging/log_lambda_metrics.py
wavelength/logging/logging_util.py
wavelength/logging/slog.py
wavelength/logging/util/__init__.py
wavelength/logging/util/cast_checks.py
wavelength/model/__init__.py
wavelength/model/model_base.py
wavelength/model/util.py
wavelength/util/__init__.py
wavelength/util/dict_differ.py
wavelength-0.0.11.dist-info/METADATA
wavelength-0.0.11.dist-info/WHEEL
wavelength-0.0.11.dist-info/top_level.txt
wavelength-0.0.11.dist-info/RECORD
