Metadata-Version: 2.1
Name: wavelength
Version: 0.0.11
Summary: Common Utilities for Serverless Development
Home-page: UNKNOWN
Author: Wavelength Serverless Team
Author-email: dev@marrow-systems.com
License: UNKNOWN
Keywords: Lambda,Serverless,AWS,Dynamo,Structured Logging
Platform: UNKNOWN
Classifier: Programming Language :: Python :: 3
Requires-Dist: structlog (==18.1.0)
Requires-Dist: jsonschema (==2.6.0)
Requires-Dist: cachetools (==2.0.0)
Requires-Dist: boto (==2.49.0)
Requires-Dist: boto3 (==1.14.7)
Requires-Dist: botocore (==1.17.7)
Requires-Dist: requests (==2.24.0)
Requires-Dist: pymemcache (==1.4.3)
Requires-Dist: retrying (==1.3.3)
Requires-Dist: schematics (==2.1.0)
Requires-Dist: pynamodb (==4.3.2)
Requires-Dist: graphene (==2.1.8)
Requires-Dist: graphene-pynamodb (==2.3.0)
Requires-Dist: arrow (==0.12.1)
Requires-Dist: bravado-core (==5.0.7)
Requires-Dist: schleppy (==1.0.2)
Requires-Dist: simplejson (==3.16)
